setup.py
Gater/__init__.py
Gater.egg-info/PKG-INFO
Gater.egg-info/SOURCES.txt
Gater.egg-info/dependency_links.txt
Gater.egg-info/requires.txt
Gater.egg-info/top_level.txt