Metadata-Version: 1.0
Name: Gater
Version: 0.0.4
Summary: gate.io history data downloader
Home-page: UNKNOWN
Author: turkey sui
Author-email: suiminyan@gmail.com
License: UNKNOWN
Platform: UNKNOWN
